pykimix/__init__.py
pykimix/animation.py
pykimix/audio_manager.py
pykimix/core.py
pykimix/gpu.py
pykimix/input_manager.py
pykimix/integration_engine.py
pykimix/rendering.py
pykimix/resources.py
pykimix/scene_manager.py
pykimix/utils.py
pykimix/window_guard.py
pykimix/assets/fonts/font1.ttf
pykimix/assets/fonts/font2.ttf
pykimix/assets/fonts/font3.ttf
pykimix/assets/fonts/font4.ttf
pykimix/c_core/cmakelists.txt
pykimix/c_core/libpykimix.so
pykimix/c_core/include/pykimix_gpu.h
pykimix/c_core/include/pykimix_math.h
pykimix/c_core/include/pykimix_utils.h
pykimix/c_core/src/entry.cpp
pykimix/c_core/src/gpu.cpp
pykimix/c_core/src/math.cpp
pykimix/c_core/src/utils.cpp
pykimix-0.4.32.dist-info/METADATA
pykimix-0.4.32.dist-info/WHEEL
pykimix-0.4.32.dist-info/top_level.txt
pykimix-0.4.32.dist-info/RECORD
