Metadata-Version: 2.4
Name: pykimix
Version: 0.4.32
Summary: Python engine integrating Pygame and Kivy with optional native acceleration.
Author: StormTheGuy
License: MIT
Project-URL: Homepage, https://github.com/stormm-dev/pykimix
Project-URL: Source, https://github.com/stormm-dev/pykimix
Project-URL: Issues, https://github.com/stormm-dev/pykimix/issues
Requires-Python: >=3.8
